siscom/__init__.py
siscom/cli.py
siscom/searcher.py
siscom-0.0.8.dist-info/METADATA
siscom-0.0.8.dist-info/WHEEL
siscom-0.0.8.dist-info/entry_points.txt
siscom-0.0.8.dist-info/top_level.txt
siscom-0.0.8.dist-info/RECORD
