Metadata-Version: 2.4
Name: siscom
Version: 0.0.8
Summary: Add your description here
Requires-Python: >=3.11
Requires-Dist: rich>=14.1.0
